anticipate/__init__.py
anticipate/adapt.py
anticipate/decorators.py
anticipate/exceptions.py
anticipate-0.9.1.dist-info/LICENSE
anticipate-0.9.1.dist-info/METADATA
anticipate-0.9.1.dist-info/WHEEL
anticipate-0.9.1.dist-info/top_level.txt
anticipate-0.9.1.dist-info/RECORD
