Metadata-Version: 2.1
Name: anticipate
Version: 0.9.1
Summary: A type checking and adapting library
Home-page: http://github.com/six8/anticipate
Author: Mike Thornton
Author-email: six8@devdetails.com
License: BSD
Download-URL: http://github.com/six8/anticipate
Keywords: packaging
Platform: UNKNOWN
Classifier: Programming Language :: Python
Classifier: Intended Audience :: Developers
Classifier: Natural Language :: English
Classifier: Topic :: Software Development :: Libraries :: Python Modules
Classifier: Programming Language :: Python
Classifier: Programming Language :: Python :: 2.7
Classifier: Programming Language :: Python :: 3
Classifier: Programming Language :: Python :: 3.6
Classifier: Programming Language :: Python :: 3.7
Classifier: Operating System :: OS Independent
Classifier: License :: OSI Approved :: BSD License
Requires-Dist: future (==0.17.1)
Provides-Extra: test
Requires-Dist: pytest ; extra == 'test'
